qstd_core/__init__.py
qstd_core/exceptions/__init__.py
qstd_core/exceptions/base.py
qstd_core/exceptions/localization.py
qstd_core/localization/__init__.py
qstd_core/logger/__init__.py
qstd_core/marshmallow/__init__.py
qstd_core/marshmallow/fields.py
qstd_core/marshmallow/schema.py
qstd_core/marshmallow/validate.py
qstd_core/openapi/__init__.py
qstd_core/openapi/decorators.py
qstd_core/openapi/enum.py
qstd_core/openapi/router.py
qstd_core/openapi/spec.py
qstd_core/openapi/utils.py
qstd_core/sanic/__init__.py
qstd_core/sanic/request/__init__.py
qstd_core/sanic/server/__init__.py
qstd_core/sanic/server/utils.py
qstd_core/validator/ValidatorABS.py
qstd_core/validator/ValidatorMarshmallow.py
qstd_core/validator/ValidatorPydantic.py
qstd_core/validator/__init__.py
qstd_core/validator/enums.py
qstd_core/validator/exceptions.py
qstd_core/validator/types.py
qstd_core-0.7.0.dist-info/LICENSE
qstd_core-0.7.0.dist-info/METADATA
qstd_core-0.7.0.dist-info/WHEEL
qstd_core-0.7.0.dist-info/top_level.txt
qstd_core-0.7.0.dist-info/RECORD
