Metadata-Version: 2.1
Name: qstd-core
Version: 0.7.0
Summary: Application core based on sanic
Home-page: https://github.com/QuisEgoSum/qstd-core
Author: QuisEgoSum
Author-email: subbotin.evdokim@gmail.com
License: MIT
Keywords: sanic
Requires-Python: >=3.7
License-File: LICENSE
Requires-Dist: sanic (>=22.0.0)
Requires-Dist: marshmallow (>=3.0.0)
Requires-Dist: pydantic (>=1.10.0)
Requires-Dist: PyYAML
Requires-Dist: jsonref
